Metadata-Version: 2.1
Name: mlflow-devlibx
Version: 1.22.8
Summary: MLflow: A Platform for ML Development and Productionization
Home-page: https://mlflow.org/
Author: Databricks
License: Apache License 2.0
Project-URL: Bug Tracker, https://github.com/mlflow/mlflow/issues
Project-URL: Documentation, https://mlflow.org/docs/latest/index.html
Project-URL: Source Code, https://github.com/mlflow/mlflow
Keywords: ml ai databricks
Platform: UNKNOWN
Classifier: Intended Audience :: Developers
Classifier: Programming Language :: Python :: 3.6
Requires-Python: >=3.6
License-File: LICENSE.txt
Requires-Dist: click (>=7.0)
Requires-Dist: cloudpickle
Requires-Dist: databricks-cli (>=0.8.7)
Requires-Dist: entrypoints
Requires-Dist: gitpython (>=2.1.0)
Requires-Dist: pyyaml (>=5.1)
Requires-Dist: protobuf (>=3.7.0)
Requires-Dist: pytz
Requires-Dist: requests (>=2.17.3)
Requires-Dist: packaging
Requires-Dist: importlib-metadata (!=4.7.0,>=3.7.0)
Requires-Dist: alembic (<=1.4.1)
Requires-Dist: docker (>=4.0.0)
Requires-Dist: Flask
Requires-Dist: numpy
Requires-Dist: scipy
Requires-Dist: pandas
Requires-Dist: prometheus-flask-exporter
Requires-Dist: querystring-parser
Requires-Dist: sqlparse (>=0.3.1)
Requires-Dist: sqlalchemy
Requires-Dist: flask-cdc-devlibx (>=0.0.10)
Requires-Dist: flask-cors
Requires-Dist: pymysql
Requires-Dist: boto3
Requires-Dist: gunicorn ; platform_system != "Windows"
Requires-Dist: waitress ; platform_system == "Windows"
Provides-Extra: aliyun-oss
Requires-Dist: aliyunstoreplugin ; extra == 'aliyun-oss'
Provides-Extra: extras
Requires-Dist: scikit-learn ; extra == 'extras'
Requires-Dist: pyarrow ; extra == 'extras'
Requires-Dist: boto3 ; extra == 'extras'
Requires-Dist: google-cloud-storage ; extra == 'extras'
Requires-Dist: azureml-core (>=1.2.0) ; extra == 'extras'
Requires-Dist: pysftp ; extra == 'extras'
Requires-Dist: kubernetes ; extra == 'extras'
Requires-Dist: mlserver (>=0.5.3) ; extra == 'extras'
Requires-Dist: mlserver-mlflow (>=0.5.3flask-cdc-devlibx>=0.0.10) ; extra == 'extras'
Requires-Dist: flask-cors ; extra == 'extras'
Provides-Extra: sqlserver
Requires-Dist: mlflow-dbstore ; extra == 'sqlserver'
